Metadata-Version: 1.0
Name: gitls
Version: 0.0.1
Summary: Command line tool for listing git repositories on your machine.
Home-page: https://github.com/lzakharov/gitls
Author: Lev Zakharov
Author-email: l.j.zakharov@gmail.com
License: MIT License
